rrhfoem04/__init__.py
rrhfoem04/constants.py
rrhfoem04/core.py
rrhfoem04/exceptions.py
rrhfoem04/utils.py
rrhfoem04_lib-0.0.6.dist-info/licenses/LICENSE
rrhfoem04_lib-0.0.6.dist-info/METADATA
rrhfoem04_lib-0.0.6.dist-info/WHEEL
rrhfoem04_lib-0.0.6.dist-info/top_level.txt
rrhfoem04_lib-0.0.6.dist-info/RECORD
