Metadata-Version: 2.4
Name: rrhfoem04-lib
Version: 0.0.6
Summary: Python Library for interfacing with the RRHFOEM04 RFID Reader
Author: ajxv
License: MIT License
Project-URL: Repository, https://github.com/ajxv/rrhfoem04-lib
Project-URL: Issues, https://github.com/ajxv/rrhfoem04-lib/issues
Classifier: Programming Language :: Python :: 3
Classifier: License :: OSI Approved :: MIT License
Classifier: Operating System :: OS Independent
Classifier: Intended Audience :: Developers
Classifier: Intended Audience :: Information Technology
Classifier: Intended Audience :: Other Audience
Requires-Python: >=3.12
License-File: LICENSE
Requires-Dist: hidapi==0.14.0.post4
Requires-Dist: setuptools==75.6.0
Dynamic: license-file
